fjformer/__init__.py
fjformer/checkpoint/__init__.py
fjformer/checkpoint/_load.py
fjformer/checkpoint/streamer.py
fjformer/core/__init__.py
fjformer/core/errors.py
fjformer/core/implicit_array.py
fjformer/core/symbols.py
fjformer/core/types.py
fjformer/core/utilities.py
fjformer/dtypes/__init__.py
fjformer/dtypes/a4q/__init__.py
fjformer/dtypes/a4q/a4q.py
fjformer/dtypes/a8q/__init__.py
fjformer/dtypes/a8q/a8q.py
fjformer/dtypes/array8bit/__init__.py
fjformer/dtypes/array8bit/array8bit.py
fjformer/dtypes/array8lt/__init__.py
fjformer/dtypes/array8lt/array8lt.py
fjformer/dtypes/arraynf4/__init__.py
fjformer/dtypes/arraynf4/arraynf4.py
fjformer/functions/__init__.py
fjformer/functions/_functions.py
fjformer/functions/loss_functions.py
fjformer/jax_triton/__init__.py
fjformer/jax_triton/lib.py
fjformer/jaxpruner/__init__.py
fjformer/jaxpruner/algorithms/__init__.py
fjformer/jaxpruner/algorithms/global_pruners.py
fjformer/jaxpruner/algorithms/global_pruners_test.py
fjformer/jaxpruner/algorithms/pruners.py
fjformer/jaxpruner/algorithms/pruners_test.py
fjformer/jaxpruner/algorithms/sparse_trainers.py
fjformer/jaxpruner/algorithms/sparse_trainers_test.py
fjformer/jaxpruner/algorithms/ste.py
fjformer/jaxpruner/algorithms/ste_test.py
fjformer/jaxpruner/api.py
fjformer/jaxpruner/api_test.py
fjformer/jaxpruner/base_updater.py
fjformer/jaxpruner/base_updater_test.py
fjformer/jaxpruner/mask_calculator.py
fjformer/jaxpruner/mask_calculator_test.py
fjformer/jaxpruner/sparsity_distributions.py
fjformer/jaxpruner/sparsity_distributions_test.py
fjformer/jaxpruner/sparsity_schedules.py
fjformer/jaxpruner/sparsity_schedules_test.py
fjformer/jaxpruner/sparsity_types.py
fjformer/jaxpruner/utils.py
fjformer/jaxpruner/utils_test.py
fjformer/kernels/__init__.py
fjformer/kernels/cpu_ops/__init__.py
fjformer/kernels/cpu_ops/jax_flash_attention_2.py
fjformer/kernels/flash_attention_2.py
fjformer/kernels/gemm.py
fjformer/kernels/gpu_ops/__init__.py
fjformer-0.0.91.dist-info/LICENSE
fjformer-0.0.91.dist-info/METADATA
fjformer-0.0.91.dist-info/WHEEL
fjformer-0.0.91.dist-info/RECORD
