Metadata-Version: 2.1
Name: fjformer
Version: 0.0.91
Summary: Embark on a journey of paralleled/unparalleled computational prowess with FJFormer in JAX
Home-page: https://github.com/erfanzar/FJFormer
License: Apache-2.0
Keywords: JAX,Deep Learning,Machine Learning,Flax,XLA
Author: Erfan Zare Chavoshi
Author-email: Erfanzare810@gmail.com
Requires-Python: >=3.10,<4.0
Classifier: Development Status :: 3 - Alpha
Classifier: Intended Audience :: Developers
Classifier: License :: OSI Approved :: Apache Software License
Classifier: Programming Language :: Python :: 3
Classifier: Programming Language :: Python :: 3.10
Classifier: Programming Language :: Python :: 3.11
Classifier: Programming Language :: Python :: 3.12
Classifier: Programming Language :: Python :: 3.13
Classifier: Topic :: Scientific/Engineering :: Artificial Intelligence
Requires-Dist: aqtp (>=0.8.2,<0.9.0)
Requires-Dist: chex (>=0.1.7)
Requires-Dist: einops (==0.8.0)
Requires-Dist: flax (>=0.8.0)
Requires-Dist: ipython (>=8.17.2,<8.18.0)
Requires-Dist: jax (>=0.4.34)
Requires-Dist: jaxlib (>=0.4.34)
Requires-Dist: ml-collections (==0.1.1)
Requires-Dist: msgpack (>=1.0.7,<1.1.0)
Requires-Dist: optax (>=0.2.2,<0.3.0)
Requires-Dist: plum-dispatch (==2.3.2)
Requires-Dist: safetensors
Requires-Dist: scipy (==1.13.1)
Requires-Dist: tqdm (>=4.64.1,<4.65.0)
Requires-Dist: triton (>=3.0)
Requires-Dist: typing (>=3.7.4.3,<3.8.0.0)
Project-URL: Documentation, https://erfanzar.github.io/FJFormer
Project-URL: Repository, https://github.com/erfanzar/FJFormer
